DataFactory/__init__.py
DataFactory/sqlinterface.cpython-310-x86_64-linux-gnu.so
models/__init__.py
models/alert_providers.cpython-310-x86_64-linux-gnu.so
models/api.py
models/approval_rate.cpython-310-x86_64-linux-gnu.so
models/banks.cpython-310-x86_64-linux-gnu.so
models/billing_models.cpython-310-x86_64-linux-gnu.so
models/bins.cpython-310-x86_64-linux-gnu.so
models/campaign_balancer.cpython-310-x86_64-linux-gnu.so
models/campaigns.cpython-310-x86_64-linux-gnu.so
models/capfill.cpython-310-x86_64-linux-gnu.so
models/clients.cpython-310-x86_64-linux-gnu.so
models/color_index.cpython-310-x86_64-linux-gnu.so
models/config.py
models/corp_cascade.cpython-310-x86_64-linux-gnu.so
models/corps.cpython-310-x86_64-linux-gnu.so
models/crm_errors.cpython-310-x86_64-linux-gnu.so
models/custom_shipping.cpython-310-x86_64-linux-gnu.so
models/db.cpython-310-x86_64-linux-gnu.so
models/discount_stats.cpython-310-x86_64-linux-gnu.so
models/discounter.cpython-310-x86_64-linux-gnu.so
models/email_reconfs.cpython-310-x86_64-linux-gnu.so
models/exception_log.cpython-310-x86_64-linux-gnu.so
models/filter_index.cpython-310-x86_64-linux-gnu.so
models/gateway_providers.cpython-310-x86_64-linux-gnu.so
models/gateways.cpython-310-x86_64-linux-gnu.so
models/hard_declines.cpython-310-x86_64-linux-gnu.so
models/initials.cpython-310-x86_64-linux-gnu.so
models/instance_data.cpython-310-x86_64-linux-gnu.so
models/invoices.cpython-310-x86_64-linux-gnu.so
models/iso.cpython-310-x86_64-linux-gnu.so
models/logga.cpython-310-x86_64-linux-gnu.so
models/master_campaigns.cpython-310-x86_64-linux-gnu.so
models/mc_promo.cpython-310-x86_64-linux-gnu.so
models/mids.cpython-310-x86_64-linux-gnu.so
models/offer_globals.cpython-310-x86_64-linux-gnu.so
models/offers.cpython-310-x86_64-linux-gnu.so
models/order_actions.cpython-310-x86_64-linux-gnu.so
models/order_cycles.cpython-310-x86_64-linux-gnu.so
models/order_processing.cpython-310-x86_64-linux-gnu.so
models/orders.cpython-310-x86_64-linux-gnu.so
modelswrkpi-10.7.4.dist-info/METADATA
modelswrkpi-10.7.4.dist-info/WHEEL
modelswrkpi-10.7.4.dist-info/top_level.txt
modelswrkpi-10.7.4.dist-info/RECORD
