Metadata-Version: 2.4
Name: modelswrkpi
Version: 10.7.4
Author: Kelly Kapowski
Requires-Python: >=3.10
Requires-Dist: psycopg2
Requires-Dist: pandas==1.5.3
Requires-Dist: SQLAlchemy==1.*
Requires-Dist: Cython
Requires-Dist: cryptography<=42.0.8
Requires-Dist: requests
Requires-Dist: sshtunnel
Requires-Dist: keyrings.google.artifactregistry-auth
